livekit/plugins/directai/__init__.py
livekit/plugins/directai/_utils.py
livekit/plugins/directai/classifier.py
livekit/plugins/directai/detector.py
livekit/plugins/directai/version.py
livekit_plugins_directai-0.2.0.dist-info/METADATA
livekit_plugins_directai-0.2.0.dist-info/WHEEL
livekit_plugins_directai-0.2.0.dist-info/top_level.txt
livekit_plugins_directai-0.2.0.dist-info/RECORD
