Metadata-Version: 2.1
Name: livekit-plugins-directai
Version: 0.2.0
Summary: Agent Framework plugin for accessing vision models from DirectAI
Home-page: https://github.com/livekit/agents
License: Apache-2.0
Project-URL: Documentation, https://docs.livekit.io
Project-URL: Website, https://livekit.io/
Project-URL: Source, https://github.com/livekit/agents
Keywords: webrtc,realtime,audio,video,livekit,directai
Classifier: Intended Audience :: Developers
Classifier: License :: OSI Approved :: Apache Software License
Classifier: Topic :: Multimedia :: Sound/Audio
Classifier: Topic :: Multimedia :: Video
Classifier: Topic :: Scientific/Engineering :: Artificial Intelligence
Classifier: Programming Language :: Python :: 3
Classifier: Programming Language :: Python :: 3.8
Classifier: Programming Language :: Python :: 3.9
Classifier: Programming Language :: Python :: 3.10
Classifier: Programming Language :: Python :: 3 :: Only
Requires-Python: >=3.8.0
Requires-Dist: livekit >=0.9.0
Requires-Dist: livekit-agents >=0.3.0
Requires-Dist: aiohttp <4,>=3
Requires-Dist: Pillow <11,>=10
